deconstruct/__init__.py
deconstruct/meta.py
deconstruct/struct.py
deconstruct/types.py
deconstruct-0.6.dist-info/LICENSE.md
deconstruct-0.6.dist-info/METADATA
deconstruct-0.6.dist-info/WHEEL
deconstruct-0.6.dist-info/top_level.txt
deconstruct-0.6.dist-info/RECORD
