Metadata-Version: 2.1
Name: deconstruct
Version: 0.6
Summary: Pythonic C-style structs for parsing binary data
Home-page: https://github.com/biqqles/deconstruct
Author: biqqles
Author-email: biqqles@protonmail.com
License: UNKNOWN
Platform: UNKNOWN
Classifier: Programming Language :: Python :: 3
Classifier: License :: OSI Approved :: Mozilla Public License 2.0 (MPL 2.0)
Classifier: Operating System :: OS Independent
Classifier: Development Status :: 5 - Production/Stable
Requires-Python: >=3.6
